folder_scanner/__init__.py
folder_scanner/scanner.py
folderscanner-2025.4.231612.dist-info/licenses/LICENSE
folderscanner-2025.4.231612.dist-info/METADATA
folderscanner-2025.4.231612.dist-info/WHEEL
folderscanner-2025.4.231612.dist-info/top_level.txt
folderscanner-2025.4.231612.dist-info/RECORD
